crisp_api/__init__.py
crisp_api/errors/__init__.py
crisp_api/errors/route.py
crisp_api/resources/__init__.py
crisp_api/resources/bucket.py
crisp_api/resources/plugin.py
crisp_api/resources/website.py
crisp_api-1.1.19.dist-info/AUTHORS
crisp_api-1.1.19.dist-info/LICENSE
crisp_api-1.1.19.dist-info/METADATA
crisp_api-1.1.19.dist-info/WHEEL
crisp_api-1.1.19.dist-info/top_level.txt
crisp_api-1.1.19.dist-info/RECORD
