Metadata-Version: 2.1
Name: crisp-api
Version: 1.1.19
Summary: Crisp API Python.
Home-page: https://github.com/crisp-im/python-crisp-api
Author: Valerian Saliou
Author-email: valerian@valeriansaliou.name
License: MIT - http://opensource.org/licenses/mit-license.php
Classifier: Environment :: Web Environment
Classifier: Intended Audience :: Developers
Classifier: Natural Language :: English
Classifier: Programming Language :: Python
License-File: LICENSE
License-File: AUTHORS
Requires-Dist: requests
